{
  "Key": "white_market",
  "HighlightClickEntity": "white_market_dealer",

  "If": [],
  "Equals": ["wmarket","=", 0],
  "Skip": "Intro",
  "Skip": "Menu",

  "Comment": "Intro",
  "Wait": 10,
  "Dialog": [{"&6&lKnight of PumkinPie": "Heyyo~"}],
  "Wait": 10,
  "Dialog": [{"&6&lKnight of PumkinPie": "Keep an eye out while wandering around, there is a shady figure in hiding."}],
  "Wait": 10,
  "Dialog": [{"&6&lKnight of PumkinPie": "He is a wanted man and should be brought to justice."}],
  "Wait": 10,
  "Dialog": [{"&6&lKnight of PumkinPie": "Would you mind helping me out and find him?"}],
  "Wait": 10,
  "SendMessageOptions": [ -1, "&6Yes", "&cNo" ],
  "Skip": "Yes",
  "Skip": "No",

  "Comment": "Yes",
  "Dialog": [{"&6&lKnight of PumkinPie": "Awesome, if you find him please report him to the authories so they can arrest him."}],
  "Wait": 10,
  "Dialog": [{"&6&lKnight of PumkinPie": "Come back when you have some apples for me."}],
  "Wait": 10,
  "SetPersistent": ["wmarket", 1],
  "Leave": "white_market",

  "Comment": "No",
  "Dialog": [{"&6&lKnight of PumkinPie": "That's okay... We will find him with out your help..."}],
  "Wait": 10,
  "Dialog": [{"&6&lKnight of PumkinPie": "Come back when you have some apples for me."}],
  "Wait": 10,
  "SetPersistent": ["wmarket", 1],
  "Leave": "white_market",

  "Comment": "Menu",
  "Start": "wmarket_menu_0"

}
